{"sample_0": ["sortedNo, the above two code snippets are not semantically equivalent."], "sample_1": ["assert f('bcksrut', 'q') == \"bcksrutq\"```"], "sample_2": ["processedNo, the above two code snippets are not semantically equivalent."], "sample_3": ["```"], "sample_4": ["``````"], "sample_5": ["```"], "sample_6": ["```No, the above two code snippets are not semantically equivalent."], "sample_7": ["assert f([1, 1, 2, 2]) == [1, 1, 2, 2, 2, 2]```"], "sample_8": ["No, the above two code snippets are not semantically equivalent."], "sample_9": [""], "sample_10": ["```"], "sample_11": ["No, the above two code snippets are not semantically equivalent."], "sample_12": ["assert f([6, 2, 7, 1], 6) == 0```"], "sample_13": ["No, the above two code snippets are not semantically equivalent."], "sample_14": ["No, the above two code snippets are not semantically equivalent."], "sample_15": ["``````"], "sample_16": ["assert f('No, the above two code snippets are not semantically equivalent."], "sample_17": ["assert f(\"7\", 10) == \" 7 7 7 7 7 7 7 7 7\"```"], "sample_18": ["assert f('happy', 'ha') == \"appy\"```"], "sample_19": ["assert f(6,8,8) == \"6,8,8\"```"], "sample_20": ["assert f([44, 34, 23, 82, 24, 11, 63, 99], 4, 15) == [44, 34, 23, 15, 82, 24, 11, 63, 99]```"], "sample_21": ["No, the above two code snippets are not semantically equivalent."], "sample_22": ["No, the above two code snippets are not semantically equivalent."], "sample_23": ["assert f('o') == \"O\"```"], "sample_24": ["No, the above two code snippets are not semantically equivalent."], "sample_25": ["assert f([2, 0]) == False```"], "sample_26": ["``````"], "sample_27": ["```python```"], "sample_28": ["assert f(\"vsnlygltaw\") == \"VsNlYGlTaW\"```"], "sample_29": ["```"], "sample_30": ["No, the above two code snippets are not semantically equivalent."], "sample_31": ["``````"], "sample_32": ["``````"], "sample_33": ["assert f(372359) == \"104104104372359\"```"], "sample_34": ["```"], "sample_35": ["assert f(['k', 'x', 'c', 'x', 'x', 'b', 'l', 'f', 'r', 'n', 'g']) == [0, 3, 1, 3, 2, 1, 0, 0, 0, 0, 0]```"], "sample_36": ["No, the above two code snippets are not semantically equivalent."], "sample_37": ["```"], "sample_38": ["```"], "sample_39": ["``````"], "sample_40": ["assert f(\"aboba 212 has 0 digits\") == 2```"], "sample_41": ["``````python``````````````````````````````````````````````````````````````````````````````````````````````````````````````````````````````````````````````````````````````````````````````````````````````````````````````````````````````````````````````````````````````````````````````````````````````````````````````````````````````````````````````````````````````````````````````````````````````````````````````````````````````````````````````````````````````````````````````````````````````````````````````````````````````````````````````````````````````````````````````````````````````````````````````````````````````````````````````````````````````````````````````````````````````````````````````````````````````````````````````````````````````````````````````````````````````````````````````````````````````````````````````````````````````````````````````````````````````````````````````````````````````````````````````````````````````````````````````````````````````````````````````````````````````````````````````````````````````````````````````````````````````````````````````````````````````````````````````````````````````````````````````````````````````````````````````````````````````````````````````````````````````````````````````````````````````````````````````````````````````````````````````````````````````````````````````````````````````````````````````````````````````````````````````````````````````````````````````````````````````````````````````````````````````````````````````````````````````````````````````````````````````````````````````````````````````````````````````````````````````````````````````````````````````````````````````````````````````````````````````````````````````````````````````````````````````````````````````````````````````````````````````````````````````````````````````````````````````````````````````````````````````````````````````````````````````````````````````````````````````````````````````````````````````````````````````````````````````````````````````````````````````````````````````````````````````````````````````````````````````````````````````````````````````````````````````````````````````````````````````````````````````````````````````````````````````````````````````````````````````````````````````````````````````````````````````````````````````````````````````````````````````````````````````````````````````````````````````````````````````````````````````````````````````````````````````````````````````````````````````````````````````````````````````````````````````````````````````````````````````````````````````````````````````````````````````````````````````````````````````````````````````````````````````````````````````````````````````````````````````````````````````````````````````````````````````````````````"], "sample_42": ["assert f({}) == {}``````python```````````````````````````````````````````````````````````````````````````````````````````````````````````````````````````````````````````````````````````````````````````````````````````````````````````````````````````````````````````````````````````````````````````````````````````````````````````````````````````````````````````````````````````````````````````````````````````````````````````````````````````````````````````````````````````````````````````````````````````````````````````````````````````````````````````````````````````````````````````````````````````````````````````````````````````````````````````````````````````````````````````````````````````````````````````````````````````````````````````````````````````````````````````````````````````````````````````````````````````````````````````````````````````````````````````````````````````````````````````````````````````````````````````````````````````````````````````````````````````````````````````````````````````````````````````````````````````````````````````````````````````````````````````````````````````````````````````````````````````````````````````````````````````````````````````````````````````````````````````````````````````````````````````````````````````````````````````````````````````````````````````````````````````````````````````````````````````````````````````````````````````````````````````````````````````````````````````````````````````````````````````````````````````````````````````````````````````````````````````````````````````````````````````````````````````````````````````````````````````````````````````````````````````````````````````````````````````````````````````````````````````````````````````````````````````````````````````````````````````````````````````````````````````````````````````````````````````````````````````````````````````````````````````````````````````````````````````````````````````````````````````````````````````````````````````````````````````````````````````````````````````````````````````````````````````````````````````````````````````````````````````````````````````````````````````````````````````````````````````````````````````````````````````````````````````````````````````````````````````````````````````````````````````````````````````````````````````````````````````````````````````````````````````````````````````````````````````````````````````````````````````````````````````````````````````````````````````````````````````````````````````````````````````````````````````````````````````````````````````````````````````````````````````````````````````````````````````````````````````````````````````````````````````````````````````````````````````````````````````````````````````````````````````````````````````"], "sample_43": ["```"], "sample_44": ["assert f('Hey DUdE THis $nd^ &*&this@#') == \"hEy dUDe tHiS $ND^ &*&THIS@#\"```"], "sample_45": ["```python```"], "sample_46": ["assert f({'b': 1, 'a': 2}) == ['a', 2, 'b', 1]```"], "sample_47": ["```No, the above two code snippets are not semantically equivalent."], "sample_48": ["```"], "sample_49": ["assert f(\"398 Is A Poor Year To Sow\") == \"mixed\"```"], "sample_50": ["```"], "sample_51": ["assert f('--4yrw 251-//4 6p') == \"152\"```"], "sample_52": ["```"], "sample_53": ["return count + variableNo, the above two code snippets are not semantically equivalent."], "sample_54": ["assert f([1, 3]) == [1, 3, 3]``````python```````````````````````````````````````````````````````````````````````````````````````````````````````````````````````````````````````````````````````````````````````````````````````````````````````````````````````````````````````````````````````````````````````````````````````````````````````````````````````````````````````````````````````````````````````````````````````````````````````````````````````````````````````````````````````````````````````````````````````````````````````````````````````````````````````````````````````````````````````````````````````````````````````````````````````````````````````````````````````````````````````````````````````````````````````````````````````````````````````````````````````````````````````````````````````````````````````````````````````````````````````````````````````````````````````````````````````````````````````````````````````````````````````````````````````````````````````````````````````````````````````````````````````````````````````````````````````````````````````````````````````````````````````````````````````````````````````````````````````````````````````````````````````````````````````````````````````````````````````````````````````````````````````````````````````````````````````````````````````````````````````````````````````````````````````````````````````````````````````````````````````````````````````````````````````````````````````````````````````````````````````````````````````````````````````````````````````````````````````````````````````````````````````````````````````````````````````````````````````````````````````````````````````````````````````````````````````````````````````````````````````````````````````````````````````````````````````````````````````````````````````````````````````````````````````````````````````````````````````````````````````````````````````````````````````````````````````````````````````````````````````````````````````````````````````````````````````````````````````````````````````````````````````````````````````````````````````````````````````````````````````````````````````````````````````````````````````````````````````````````````````````````````````````````````````````````````````````````````````````````````````````````````````````````````````````````````````````````````````````````````````````````````````````````````````````````````````````````````````````````````````````````````````````````````````````````````````````````````````````````````````````````````````````````````````````````````````````````````````````````````````````````````````````````````````````````````````````````````````````````````````````````````````````````````````````````````````````````````````````````````````````````````````````````````````````"], "sample_55": ["```"], "sample_56": ["assert f({'9m':2, 'mA':1, '10K':2, 'Lk':2}, 1) == ['9m', 'mA', 'Lk', '10K']```"], "sample_57": ["```"], "sample_58": ["```"], "sample_59": ["```python```python```python```python```python```python```python```python```python```python```python```python```python```python```python```python```python```python```python```python```python```python```python```python```python```python```python```python```python```python```python```python```python```python```python```python```python```python```python```python```python```python```python```python```python```python```python```python```python```python```python```python```python```python```python```python```python```python```python```python```python```python```python```python```python```python```python```python```python```python```python```python```python```python```python```python```python```python```python```python```python```python```python```python```python```python```python```python```python```python```python```python```python```python```python```python```python```python```python```python```python```python```python```python```python```python```python```python```python```python```python```python```python```python```python```python```python```python```python```python```python```python```python```python```python```python```python```python```python```python```python```python```python```python```python```python```python```python```python```python```python```python```python```python```python```python```python```python```python```python```python```python```python```python```python```python```python```python```python```python```python```python```python```python```python```python```python```python```python```python```python```python```python```python```python```python```python```python```python```python```python```python```python```python```python```python```python```python```python```python```python```python```python```python```python```python```python```python```python```python```python```python```python```python```python```python```python```python```python```python```python```python```python```python```python```python```python```python```python```python```python```python```python```python```python```python```python```python```python```python```python```python```python```python```python```python```python```python```python```python```python```python```python```python```python```python```python```python```python```python```python```python```python```python```python```python```python```python```python```python```python```python```python```python```python```python```python```python```python```python```python```python```python```python```python```python```python```python```python```python```python```python```python```python```python```python```python```python```python```python```python```python```python```python```python```python```python```python```python```python```python```python```python```python```python```python```python```python```python```python```python```python```python```python```python```python```python```python```python```python```python```python```python```python```python```python```python```python```python```python```python```python```python```python```python```python```python```python```python```python```python```python```python```python```python```python```python```python```python```python```python```python```python```python```python```python```python```python```python```python```python```python```python```python```python```python```python```python```python```python```python```python```python```python```python```python```python```python```python```python```python```python```python```python```python```python```python```python```python```python```python```python```python```python```python```python```python```python```python```python```python```python```python```python```python```python```python```python```python```python```python```python```python```python```python```python```python```python```python```python```python```python```python```python```python```python```python```python```python```python```python```python```python```python```python```python```python```python```python```python"], "sample_60": ["assert f('String matching is a big part of RexEx library.') == \"Sg-i-m-a-t-c-hNo, the above two code snippets are not semantically equivalent."], "sample_61": ["return reversedNo, the above two code snippets are not semantically equivalent."], "sample_62": ["```"], "sample_63": ["assert f(\"papera\") == \"pApperA\"```"], "sample_64": ["assert f([]) == []```"], "sample_65": ["```"], "sample_66": ["No, the above two code snippets are not semantically equivalent."], "sample_67": ["assert f({'Iron Man': 4, 'Captain America': 3, 'Black Panther': 0,'Thor': 1, 'Ant-Man': 6}, 'Iron Man') == \"Captain America\"```"], "sample_68": ["```"], "sample_69": ["`````````````````````````````````````````````````````````````````````````````````````````````````````````````````````````````````````````````````````````````````````````````````````````````````````````````````````````````````````````````````````````````````````````````````````````````````````````````````````````````````````````````````````````````````````````````````````````````````````````````````````````````````````````````````````````````````````````````````````````````````````````````````````````````````````````````````````````````````````````````````````````````````````````````````````````````````````````````````````````````````````````````````````````````````````````````````````````````````````````````````````````````````````````````````````````````````````````````````````````````````````````````````````````````````````````````````````````````````````````````````````````````````````````````````````````````````````````````````````````````````````````````````````````````````````````````````````````````````````````````````````````````````````````````````````````````````````````````````````````````````````````````````````````````````````````````````````````````````````````````````````````````````````````````````````````````````````````````````````````````````````````````````````````````````````````````````````````````````````````````````````````````````````````````````````````````````````````````````````````````````````````````````````````````````````````````````````````````````````````````````````````````````````````````````````````````````````````````````````````````````````````````````````````````````````````````````````````````````````````````````````````````````````````````````````````````````````````````````````````````````````````````````````````````````````````````````````````````````````````````````````````````````````````````````````````````````````````````````````````````````````````````````````````````````````````````````````````````````````````````````````````````````````````````````````````````````````````````````````````````````````````````````````````````````````````````````````````````````````````````````````````````````````````````````````````````````````````````````````````````````````````````````````````````````````````````````````````````````````````````````````````````````````````````````````````````````````````````````````````````````````````````````````````````````````````````````````````````````````````````````````````````````````````````````````````````````````````````````````````````````````````````````````````````````````````````````````````````````````````````````````````````````````````````````````````````````````````````````````````````````````````````````````````````````````````````````````````````"], "sample_70": ["assert f('wdeejjjzsjsjjsxjjneddaddddddefsfd') == \"wdeejjjzsjsjjsxjjhaystacksddaddddddefsfd\"```"], "sample_71": ["``````"], "sample_72": ["```"], "sample_73": ["```"], "sample_74": ["assert f('USaR') == \"usAr\"```"], "sample_75": ["descendingNo, the above two code snippets are not semantically equivalent."], "sample_76": ["```"], "sample_77": ["assert f([-6, -2, 1, -3, 0, 1]) == [-6, -2, 0]```"], "sample_78": ["No, the above two code snippets are not semantically equivalent."], "sample_79": ["assert f({'a': 1, 'b': 2, 'c': 3, 'd': 2}) == {'2: 'd', '3: 'c', '1: 'a', '2: 'b```"], "sample_80": ["```"], "sample_81": ["```"], "sample_82": ["assert f('{0}, {0}!!!', ['R', None]) == \"R, R!!!\"```"], "sample_83": ["```"], "sample_84": ["No, the above two code snippets are not semantically equivalent."], "sample_85": ["assert f(\"#Un, the above two code snippets are not semantically equivalent."], "sample_86": ["No, the above two code snippets are not semantically equivalent."], "sample_87": ["```No, the above two code snippets are not semantically equivalent."], "sample_88": ["```No, the above two code snippets are not semantically equivalent."], "sample_89": ["``````"], "sample_90": ["assert f('19', 5) == \"00019\"```"], "sample_91": ["```python```"], "sample_92": ["```No, the above two code snippets are not semantically equivalent."], "sample_93": ["```"], "sample_94": ["```"], "sample_95": ["```"], "sample_96": ["return count + variableNo, the above two code snippets are not semantically equivalent."], "sample_97": ["assert f([-4, 6, 0, 4, -7, 2, -1]) == [-1, 2, -7, 4, 0, 6, -4]```"], "sample_98": ["assert f('querist', 'u') == \"Querist\"```"], "sample_99": ["assert f([1, 3, -1, 1, -2, 6]) == [-1, 1, -2, 1, 3, -1]```"], "sample_100": ["```"], "sample_101": ["``````"], "sample_102": ["```"], "sample_103": ["```python```"], "sample_104": ["```"], "sample_105": ["assert f('coscifysu') == \"coscifys\"```"], "sample_106": ["```"], "sample_107": ["No, the above two code snippets are not semantically equivalent."], "sample_108": ["```python```"], "sample_109": ["```python```python```python```python```python```python```python```python```python```python```python```python```python```python```python```python```python```python```python```python```python```python```python```python```python```python```python```python```python```python```python```python```python```python```python```python```python```python```python```python```python```python```python```python```python```python```python```python```python```python```python```python```python```python```python```python```python```python```python```python```python```python```python```python```python```python```python```python```python```python```python```python```python```python```python```python```python```python```python```python```python```python```python```python```python```python```python```python```python```python```python```python```python```python```python```python```python```python```python```python```python```python```python```python```python```python```python```python```python```python```python```python```python```python```python```python```python```python```python```python```python```python```python```python```python```python```python```python```python```python```python```python```python```python```python```python```python```python```python```python```python```python```python```python```python```python```python```python```python```python```python```python```python```python```python```python```python```python```python```python```python```python```python```python```python```python```python```python```python```python```python```python```python```python```python```python```python```python```python```python```python```python```python```python```python```python```python```python```python```python```python```python```python```python```python```python```python```python```python```python```python```python```python```python```python```python```python```python```python```python```python```python```python```python```python```python```python```python```python```python```python```python```python```python```python```python```python```python```python```python```python```python```python```python```python```python```python```python```python```python```python```python```python```python```python```python```python```python```python```python```python```python```python```python```python```python```python```python```python```python```python```python```python```python```python```python```python```python```python```python```python```python```python```python```python```python```python```python```python```python```python```python```python```python```python```python```python```python```python```python```python```python```python```python```python```python```python```python```python```python```python```python```python```python```python```python```python```python```python```python```python```python```python```python```python```python```python```python```python```python```python```python```python```python```python```python```python```python```python```python```python```python```python```python```python```python```python```python```python```python```python```python```python```python```python```python```python```python```python```python```python```python```python```python```python```python```python```python```python```python```python```python```python```python```python```python```python```python```python```python```python```python```python```python```python```python```python```python```python```python```python```python```python```python```python```python```python```python```python```python```python```python```python```python```python```python```python```python```python```python```python```python```python```python```python```python```python```python```python```python```python```python```python```python```python```python```python```python```python```python```python```python```python```python```python```python```python```python```python```python```python```python```python```python```python```python```python```python```python```python```python```python```python```python```python```python```python```python```python```python```python```python```"], "sample_110": ["assert f('mmm34mIm', 'mm3', ',po') == \"Im,po\"```"], "sample_111": ["assert f('GENERAL NAGOOR', 5) == \"| GENERAL NAGOOR|\"```"], "sample_112": ["assert f('unrndqafi', 'c', 2) == \"unrndcafi\"```"], "sample_113": ["from scipyNo, the above two code snippets are not semantically equivalent."], "sample_114": ["assert f('coscifysu', 'cos') == \"cifysu\"```"], "sample_115": ["formatted_key_valueNo, the above two code snippets are not semantically equivalent."], "sample_116": ["```python```"], "sample_117": ["assert f(44) == ??```"], "sample_118": ["assert f([2, 2, 2, 3, 3], 2, 3) == [2, 3, 2, 2, 3, 3]```"], "sample_119": ["```"], "sample_120": ["```"], "sample_121": ["```"], "sample_122": ["``````"], "sample_123": ["assert f({2: 5, 4: 1, 3: 5, 1: 3, 5: 1}) == {1: 0, 2: 1, 3: 2, 4: 3, 5: 4}```"], "sample_124": ["No, the above two code snippets are not semantically equivalent."], "sample_125": ["```No, the above two code snippets are not semantically equivalent."], "sample_126": ["``````"], "sample_127": ["No, the above two code snippets are not semantically equivalent."], "sample_128": ["assert f('0574', 9) == \"0574zzzzz\"```"], "sample_129": ["No, the above two code snippets are not semantically equivalent."], "sample_130": ["from scipyNo, the above two code snippets are not semantically equivalent."], "sample_131": ["``````"], "sample_132": [""], "sample_133": ["assert f([2, 0, 1, 9999, 3, -5]) == [```"], "sample_134": ["assert f('xxxarmmarxx') == \"xxx ar mar xxx\"```"], "sample_135": ["assert f([2], 0, 2) == [2, 0, 2]```"], "sample_136": ["```"], "sample_137": ["```"], "sample_138": ["```"], "sample_139": ["```"], "sample_140": ["No, the above two code snippets are not semantically equivalent."], "sample_141": ["assert f(7, 5) == [5, 5, 5, 5, 5, 5, 5]``````python``````python``````python``````python``````python``````python``````python``````python``````python``````python``````python``````python``````python``````python``````python``````python``````python``````python``````python``````python``````python``````python``````python``````python``````python``````python``````python``````python``````python``````python``````python``````python``````python``````python``````python``````python``````python``````python``````python``````python``````python``````python``````python``````python``````python``````python``````python``````python``````python``````python``````python``````python``````python``````python``````python``````python``````python``````python``````python``````python``````python``````python``````python``````python``````python``````python``````python``````python``````python``````python``````python``````python``````python``````python``````python``````python``````python``````python``````python``````python``````python``````python``````python``````python``````python``````python``````python``````python``````python``````python``````python``````python``````python``````python``````python``````python``````python``````python``````python``````python``````python``````python``````python``````python``````python``````python``````python``````python``````python``````python``````python``````python``````python``````python``````python``````python``````python``````python``````python``````python``````python``````python``````python``````python``````python``````python``````python``````python``````python``````python``````python``````python``````python``````python``````python``````python``````python``````python``````python``````python``````python``````python``````python``````python``````python``````python``````python``````python``````python``````python``````python``````python``````python``````python``````python``````python``````python``````python``````python``````python``````python``````python``````python``````python``````python``````python``````python``````python``````python``````python``````python``````python``````python``````python``````python``````python``````python``````python``````python``````python``````python``````python``````python``````python``````python``````python``````python``````python``````python``````python``````python``````python``````python``````python``````python``````python``````python``````python``````python``````python``````python``````python``````python``````python``````python``````python``````python``````python``````python``````python``````python``````python``````python``````python``````python``````python``````python``````python``````python``````python``````python``````python``````python``````python``````python``````python``````python``````python``````python``````python``````python``````python``````python``````python``````python``````python``````python``````python``````python``````python``````python``````python``````python``````python``````python``````python``````python``````python``````python``````python``````python``````python``````python``````python``````python``````python``````python``````python``````python``````python``````python``````python``````python``````python``````python``````python``````python``````python``````python``````python``````python``````python``````python``````python``````python``````python``````python``````python``````python``````python``````python``````python``````python``````python``````python``````python``````python``````python``````python``````python``````python``````python``````python``````python``````python``````python``````python``````python``````python``````python``````python``````python``````python``````python``````python``````python``````python``````python``````python``````"], "sample_142": ["```"], "sample_143": [""], "sample_144": ["````````````````````````````````````````````````````````````````````````````````````````````````````````````````````````````````````````````````````````````````````````````````````````````````````````````````````````````````````````````````````````````````````````````````````````````````````````````````````````````````````````````````````````````````````````````````````````````````````````````````````````````````````````````````````````````````````````````````````````````````````````````````````````````````````````````````````````````````````````````````````````````````````````````````````````````````````````````````````````````````````````````````````````````````````````````````````````````````````````````````````````````````````````````````````````````````````````````````````````````````````````````````````````````````````````````````````````````````````````````````````````````````````````````````````````````````````````````````````````````````````````````````````````````````````````````````````````````````````````````````````````````````````````````````````````````````````````````````````````````````````````````````````````````````````````````````````````````````````````````````````````````````````````````````````````````````````````````````````````````````````````````````````````````````````````````````````````````````````````````````````````````````````````````````````````````````````````````````````````````````````````````````````````````````````````````````````````````````````````````````````````````````````````````````````````````````````````````````````````````````````````````````````````````````````````````````````````````````````````````````````````````````````````````````````````````````````````````````````````````````````````````````````````````````````````````````````````````````````````````````````````````````````````````````````````````````````````````````````````````````````````````````````````````````````````````````````````````````````````````````````````````````````````````````````````````````````````````````````````````````````````````````````````````````````````````````````````````````````````````````````````````````````````````````````````````````````````````````````````````````````````````````````````````````````````````````````````````````````````````````````````````````````````````````````````````````````````````````````````````````````````````````````````````````````````````````````````````````````````````````````````````````````````````````````````````````````````````````````````````````````````````````````````````````"], "sample_145": ["```"], "sample_146": ["```"], "sample_147": ["```"], "sample_148": ["```python```"], "sample_149": ["assert f('13:45:56', 'shift_jis') == \"bhihia\"```"], "sample_150": ["assert f('hi~', ['~', '`', 'Unrelated, the above two code snippets are not semantically equivalent."], "sample_151": ["```"], "sample_152": ["assert f([4, 5, 3, 6, 1], 5) == [4, 3, 6, 1]```"], "sample_153": ["```"], "sample_154": ["```"], "sample_155": ["assert f([1, 1, 1, 2], 3) == 0``````python``````python``````python``````python``````python``````python``````python``````python``````python``````python``````python``````python``````python``````python``````python``````python``````python``````python``````python``````python``````python``````python``````python``````python``````python``````python``````python``````python``````python``````python``````python``````python``````python``````python``````python``````python``````python``````python``````python``````python``````python``````python``````python``````python``````python``````python``````python``````python``````python``````python``````python``````python``````python``````python``````python``````python``````python``````python``````python``````python``````python``````python``````python``````python``````python``````python``````python``````python``````python``````python``````python``````python``````python``````python``````python``````python``````python``````python``````python``````python``````python``````python``````python``````python``````python``````python``````python``````python``````python``````python``````python``````python``````python``````python``````python``````python``````python``````python``````python``````python``````python``````python``````python``````python``````python``````python``````python``````python``````python``````python``````python``````python``````python``````python``````python``````python``````python``````python``````python``````python``````python``````python``````python``````python``````python``````python``````python``````python``````python``````python``````python``````python``````python``````python``````python``````python``````python``````python``````python``````python``````python``````python``````python``````python``````python``````python``````python``````python``````python``````python``````python``````python``````python``````python``````python``````python``````python``````python``````python``````python``````python``````python``````python``````python``````python``````python``````python``````python``````python``````python``````python``````python``````python``````python``````python``````python``````python``````python``````python``````python``````python``````python``````python``````python``````python``````python``````python``````python``````python``````python``````python``````python``````python``````python``````python``````python``````python``````python``````python``````python``````python``````python``````python``````python``````python``````python``````python``````python``````python``````python``````python``````python``````python``````python``````python``````python``````python``````python``````python``````python``````python``````python``````python``````python``````python``````python``````python``````python``````python``````python``````python``````python``````python``````python``````python``````python``````python``````python``````python``````python``````python``````python``````python``````python``````python``````python``````python``````python``````python``````python``````python``````python``````python``````python``````python``````python``````python``````python``````python``````python``````python``````python``````python``````python``````python``````python``````python``````python``````python``````python``````python``````python``````python``````python``````python``````python``````python``````python``````python``````python``````python``````python``````python``````python``````python``````python``````python``````python``````python``````python``````python``````python``````python``````python``````python``````python``````python``````python``````python``````python``````python``````python``````python``````python``````python``````python"], "sample_156": ["```"], "sample_157": [""], "sample_158": ["```"], "sample_159": ["No, the above two code snippets are not semantically equivalent."], "sample_160": ["No, the above two code snippets are not semantically equivalent."], "sample_161": ["``````"], "sample_162": ["```No, the above two code snippets are not semantically equivalent."], "sample_163": ["from scipyNo, the above two code snippets are not semantically equivalent."], "sample_164": ["assert f(\"fubarbaz\") == \"fubarbaz\"```"], "sample_165": ["assert f(\"cA\") == \"Ca\"```"], "sample_166": ["``````"], "sample_167": ["assert f('hypernimovichyp', 2, 2) == \"hy_per_nim_ov_ichyp\"```"], "sample_168": ["from scipyNo, the above two code snippets are not semantically equivalent."], "sample_169": ["assert f([3, 1, 9, 0, 2, 0, 8]) == [3, 1, 9, 0, 2, 8]``````python``````python``````python``````python``````python``````python``````python``````python``````python``````python``````python``````python``````python``````python``````python``````python``````python``````python``````python``````python``````python``````python``````python``````python``````python``````python``````python``````python``````python``````python``````python``````python``````python``````python``````python``````python``````python``````python``````python``````python``````python``````python``````python``````python``````python``````python``````python``````python``````python``````python``````python``````python``````python``````python``````python``````python``````python``````python``````python``````python``````python``````python``````python``````python``````python``````python``````python``````python``````python``````python``````python``````python``````python``````python``````python``````python``````python``````python``````python``````python``````python``````python``````python``````python``````python``````python``````python``````python``````python``````python``````python``````python``````python``````python``````python``````python``````python``````python``````python``````python``````python``````python``````python``````python``````python``````python``````python``````python``````python``````python``````python``````python``````python``````python``````python``````python``````python``````python``````python``````python``````python``````python``````python``````python``````python``````python``````python``````python``````python``````python``````python``````python``````python``````python``````python``````python``````python``````python``````python``````python``````python``````python``````python``````python``````python``````python``````python``````python``````python``````python``````python``````python``````python``````python``````python``````python``````python``````python``````python``````python``````python``````python``````python``````python``````python``````python``````python``````python``````python``````python``````python``````python``````python``````python``````python``````python``````python``````python``````python``````python``````python``````python``````python``````python``````python``````python``````python``````python``````python``````python``````python``````python``````python``````python``````python``````python``````python``````python``````python``````python``````python``````python``````python``````python``````python``````python``````python``````python``````python``````python``````python``````python``````python``````python``````python``````python``````python``````python``````python``````python``````python``````python``````python``````python``````python``````python``````python``````python``````python``````python``````python``````python``````python``````python``````python``````python``````python``````python``````python``````python``````python``````python``````python``````python``````python``````python``````python``````python``````python``````python``````python``````python``````python``````python``````python``````python``````python``````python``````python``````python``````python``````python``````python``````python``````python``````python``````python``````python``````python``````python``````python``````python``````python``````python``````python``````python``````python``````python``````python``````python``````python``````python``````python``````python``````python``````python``````python``````python``````python``````python``````python``````python``````python``````python``````python``````python``````python"], "sample_170": ["assert f(dict(e=1, d=2, c=3)) == (\"c\", dict(e=1, d=2))```"], "sample_171": [""], "sample_172": ["assert f(\"Where is the bot in this world?\") == 24```"], "sample_173": ["```python```python```python```python```python```python```python```python```python```python```python```python```python```python```python```python```python```python```python```python```python```python```python```python```python```python```python```python```python```python```python```python```python```python```python```python```python```python```python```python```python```python```python```python```python```python```python```python```python```python```python```python```python```python```python```python```python```python```python```python```python```python```python```python```python```python```python```python```python```python```python```python```python```python```python```python```python```python```python```python```python```python```python```python```python```python```python```python```python```python```python```python```python```python```python```python```python```python```python```python```python```python```python```python```python```python```python```python```python```python```python```python```python```python```python```python```python```python```python```python```python```python```python```python```python```python```python```python```python```python```python```python```python```python```python```python```python```python```python```python```python```python```python```python```python```python```python```python```python```python```python```python```python```python```python```python```python```python```python```python```python```python```python```python```python```python```python```python```python```python```python```python```python```python```python```python```python```python```python```python```python```python```python```python```python```python```python```python```python```python```python```python```python```python```python```python```python```python```python```python```python```python```python```python```python```python```python```python```python```python```python```python```python```python```python```python```python```python```python```python```python```python```python```python```python```python```python```python```python```python```python```python```python```python```python```python```python```python```python```python```python```python```python```python```python```python```python```python```python```python```python```python```python```python```python```python```python```python```python```python```python```python```python```python```python```python```python```python```python```python```python```python```python```python```python```python```python```python```python```python```python```python```python```python```python```python```python```python```python```python```python```python```python```python```python```python```python```python```python```python```python```python```python```python```python```python```python```python```python```python```python```python```python```python```python```python```python```python```python```python```python```python```python```python```python```python```python```python```python```python```python```python```python```python```python```python```python```python```python```python```python```python```python```python```python```python```python```python```python```python```python```python```python```python```python```python```python```python```python```python```python```python```python```python```python```python```python```python```python```python```python```python```python```python```python```python```python```python```python```python```python```python```python```python```python```python```python```python```python```python```python```python```python```python```python```python```python```python```python```python```python```python```python```python```python```python```python```python```python```python```python```python```python```python```python```python```python```python```python```python```python```python```python```python```python```python```python```python```python```python```python```python```python```python```python```python```python```python```python```python```python```python```python```python```python```python```python```python```python```python```python```python```"], "sample_174": ["assert f('a loved') == \"loved a\"```"], "sample_175": ["assert f({'aki': ['1', '5']}, 'aki', '2') == {'aki': ['1', '5', '2']}``````"], "sample_176": ["assert f([3, -2, 0]) == ??```"], "sample_177": ["assert f('ThisIsSoAtrocious') == \"18ThisIsSoAtrocious\"```"], "sample_178": ["```python```"], "sample_179": ["assert f(\"jcle oq wsnibktxpiozyxmopqkfnrfjds\") == (4, 36)```"], "sample_180": ["````````````````````````````````````````````````````````````````````````````````````````````````````````````````````````````````````````````````````````````````````````````````````````````````````````````````````````````````````````````````````````````````````````````````````````````````````````````````````````````````````````````````````````````````````````````````````````````````````````````````````````````````````````````````````````````````````````````````````````````````````````````````````````````````````````````````````````````````````````````````````````````````````````````````````````````````````````````````````````````````````````````````````````````````````````````````````````````````````````````````````````````````````````````````````````````````````````````````````````````````````````````````````````````````````````````````````````````````````````````````````````````````````````````````````````````````````````````````````````````````````````````````````````````````````````````````````````````````````````````````````````````````````````````````````````````````````````````````````````````````````````````````````````````````````````````````````````````````````````````````````````````````````````````````````````````````````````````````````````````````````````````````````````````````````````````````````````````````````````````````````````````````````````````````````````````````````````````````````````````````````````````````````````````````````````````````````````````````````````````````````````````````````````````````````````````````````````````````````````````````````````````````````````````````````````````````````````````````````````````````````````````````````````````````````````````````````````````````````````````````````````````````````````````````````````````````````````````````````````````````````````````````````````````````````````````````````````````````````````````````````````````````````````````````````````````````````````````````````````````````````````````````````````````````````````````````````````````````````````````````````````````````````````````````````````````````````````````````````````````````````````````````````````````````````````````````````````````````````````````````````````````````````````````````````````````````````````````````````````````````````````````````````````````````````````````````````````````````````````````````````````````````````````````````````````````````````````````````````````````````````````````````````````````````````````````````````````````````````````````````````````````````````````````````````````````````````````````````````````````````````````````````````````````````````````````````````````````````````````````````````````````````````````````````````````````````````"], "sample_181": ["assert f(\"r;r;r;r;r;r;r;r;r\", \"x.r\") == \"r\"``````"], "sample_182": ["```"], "sample_183": ["```"], "sample_184": ["No, the above two code snippets are not semantically equivalent."], "sample_185": ["```"], "sample_186": ["No, the above two code snippets are not semantically equivalent."], "sample_187": ["assert f('a1a8', '1', 'n2') == \"aNa8\"```"], "sample_188": ["```python```"], "sample_189": ["``````"], "sample_190": ["return modifiedNo, the above two code snippets are not semantically equivalent."], "sample_191": ["``````"], "sample_192": ["```"], "sample_193": ["assert f({}) == {}``````python``````python``````python``````python``````python``````python``````python``````python``````python``````python``````python``````python``````python``````python``````python``````python``````python``````python``````python``````python``````python``````python``````python``````python``````python``````python``````python``````python``````python``````python``````python``````python``````python``````python``````python``````python``````python``````python``````python``````python``````python``````python``````python``````python``````python``````python``````python``````python``````python``````python``````python``````python``````python``````python``````python``````python``````python``````python``````python``````python``````python``````python``````python``````python``````python``````python``````python``````python``````python``````python``````python``````python``````python``````python``````python``````python``````python``````python``````python``````python``````python``````python``````python``````python``````python``````python``````python``````python``````python``````python``````python``````python``````python``````python``````python``````python``````python``````python``````python``````python``````python``````python``````python``````python``````python``````python``````python``````python``````python``````python``````python``````python``````python``````python``````python``````python``````python``````python``````python``````python``````python``````python``````python``````python``````python``````python``````python``````python``````python``````python``````python``````python``````python``````python``````python``````python``````python``````python``````python``````python``````python``````python``````python``````python``````python``````python``````python``````python``````python``````python``````python``````python``````python``````python``````python``````python``````python``````python``````python``````python``````python``````python``````python``````python``````python``````python``````python``````python``````python``````python``````python``````python``````python``````python``````python``````python``````python``````python``````python``````python``````python``````python``````python``````python``````python``````python``````python``````python``````python``````python``````python``````python``````python``````python``````python``````python``````python``````python``````python``````python``````python``````python``````python``````python``````python``````python``````python``````python``````python``````python``````python``````python``````python``````python``````python``````python``````python``````python``````python``````python``````python``````python``````python``````python``````python``````python``````python``````python``````python``````python``````python``````python``````python``````python``````python``````python``````python``````python``````python``````python``````python``````python``````python``````python``````python``````python``````python``````python``````python``````python``````python``````python``````python``````python``````python``````python``````python``````python``````python``````python``````python``````python``````python``````python``````python``````python``````python``````python``````python``````python``````python``````python``````python``````python``````python``````python``````python``````python``````python``````python``````python``````python``````python``````python``````python``````python``````python``````python``````python``````python``````python``````python``````python``````python``````python``````python``````python``````python``````python``````python``````python``````python``````python``````python``````python``````python``````python``````python``````python"], "sample_194": ["assert f([\"avc  a .d e\"], \"\") == [\"avc a d e\"]```"], "sample_195": ["```"], "sample_196": ["assert f(\"a j c n x X k\") == False```"], "sample_197": ["```"], "sample_198": ["assert f({'i': 1, 'love': 'parakeets'}) == (False, False)```"], "sample_199": ["```"]}